pyvitals/__init__.py
pyvitals/async_main.py
pyvitals/exceptions.py
pyvitals/main.py
pyvitals-0.4.1.dist-info/LICENSE
pyvitals-0.4.1.dist-info/METADATA
pyvitals-0.4.1.dist-info/WHEEL
pyvitals-0.4.1.dist-info/top_level.txt
pyvitals-0.4.1.dist-info/RECORD
