Metadata-Version: 2.1
Name: pyvitals
Version: 0.4.1
Summary: Python tools for rdlevels
Home-page: https://github.com/huantianad/py-vitals
Author: huantian
Author-email: davidtianli@gmail.com
License: UNKNOWN
Project-URL: Bug Tracker, https://github.com/huantianad/py-vitals/issues
Platform: UNKNOWN
Classifier: Programming Language :: Python :: 3
Classifier: License :: OSI Approved :: MIT License
Classifier: Operating System :: OS Independent
Requires-Python: >=3.9
License-File: LICENSE
